django_countries/.mypy_cache/.gitignore
django_countries/.mypy_cache/3.13/@plugins_snapshot.json
django_countries/.mypy_cache/3.13/PIL/Image.data.json
django_countries/.mypy_cache/3.13/PIL/Image.meta.json
django_countries/.mypy_cache/3.13/PIL/ImageFilter.data.json
django_countries/.mypy_cache/3.13/PIL/ImageFilter.meta.json
django_countries/.mypy_cache/3.13/PIL/ImagePalette.data.json
django_countries/.mypy_cache/3.13/PIL/ImagePalette.meta.json
django_countries/.mypy_cache/3.13/PIL/PyAccess.data.json
django_countries/.mypy_cache/3.13/PIL/PyAccess.meta.json
django_countries/.mypy_cache/3.13/PIL/__init__.data.json
django_countries/.mypy_cache/3.13/PIL/__init__.meta.json
django_countries/.mypy_cache/3.13/PIL/_imaging.data.json
django_countries/.mypy_cache/3.13/PIL/_imaging.meta.json
django_countries/.mypy_cache/3.13/__future__.data.json
django_countries/.mypy_cache/3.13/__future__.meta.json
django_countries/.mypy_cache/3.13/_ast.data.json
django_countries/.mypy_cache/3.13/_ast.meta.json
django_countries/.mypy_cache/3.13/_asyncio.data.json
django_countries/.mypy_cache/3.13/_asyncio.meta.json
django_countries/.mypy_cache/3.13/_bisect.data.json
django_countries/.mypy_cache/3.13/_bisect.meta.json
django_countries/.mypy_cache/3.13/_blake2.data.json
django_countries/.mypy_cache/3.13/_blake2.meta.json
django_countries/.mypy_cache/3.13/_bz2.data.json
django_countries/.mypy_cache/3.13/_bz2.meta.json
django_countries/.mypy_cache/3.13/_codecs.data.json
django_countries/.mypy_cache/3.13/_codecs.meta.json
django_countries/.mypy_cache/3.13/_collections_abc.data.json
django_countries/.mypy_cache/3.13/_collections_abc.meta.json
django_countries/.mypy_cache/3.13/_compression.data.json
django_countries/.mypy_cache/3.13/_compression.meta.json
django_countries/.mypy_cache/3.13/_contextvars.data.json
django_countries/.mypy_cache/3.13/_contextvars.meta.json
django_countries/.mypy_cache/3.13/_csv.data.json
django_countries/.mypy_cache/3.13/_csv.meta.json
django_countries-8.1.1.dist-info/WHEEL
django_countries-8.1.1.dist-info/METADATA
django_countries-8.1.1.dist-info/RECORD
