Metadata-Version: 2.3
Name: django-countries
Version: 8.1.1
Summary: Provides a country field for Django models.
Keywords: django,countries,flags
Author: Chris Beaven
Author-email: Chris Beaven <smileychris@gmail.com>
License: MIT
Classifier: Development Status :: 5 - Production/Stable
Classifier: Environment :: Web Environment
Classifier: Intended Audience :: Developers
Classifier: License :: OSI Approved :: MIT License
Classifier: Operating System :: OS Independent
Classifier: Programming Language :: Python
Classifier: Programming Language :: Python :: 3 :: Only
Classifier: Programming Language :: Python :: 3.8
Classifier: Programming Language :: Python :: 3.9
Classifier: Programming Language :: Python :: 3.10
Classifier: Programming Language :: Python :: 3.11
Classifier: Programming Language :: Python :: 3.12
Classifier: Programming Language :: Python :: 3.13
Classifier: Framework :: Django
Classifier: Framework :: Django :: 3.2
Classifier: Framework :: Django :: 4.0
Classifier: Framework :: Django :: 4.1
Classifier: Framework :: Django :: 4.2
Classifier: Framework :: Django :: 5.0
Classifier: Framework :: Django :: 5.1
Classifier: Framework :: Django :: 5.2
Requires-Dist: asgiref
Requires-Dist: typing-extensions
Requires-Dist: pyuca ; extra == 'pyuca'
Requires-Python: >=3.8
Project-URL: Change Log, https://github.com/SmileyChris/django-countries/blob/main/CHANGES.md
Project-URL: Homepage, https://github.com/SmileyChris/django-countries/
Project-URL: Source Code, https://github.com/SmileyChris/django-countries
Project-URL: Translations, https://explore.transifex.com/smileychris/django-countries/
Provides-Extra: pyuca
